sociable_bot/__init__.py
sociable_bot/bot.py
sociable_bot/bot_async.py
sociable_bot/bot_enums.py
sociable_bot/bot_types.py
sociable_bot-0.0.103.dist-info/licenses/LICENSE.txt
sociable_bot-0.0.103.dist-info/METADATA
sociable_bot-0.0.103.dist-info/WHEEL
sociable_bot-0.0.103.dist-info/top_level.txt
sociable_bot-0.0.103.dist-info/RECORD
