Metadata-Version: 2.4
Name: sociable_bot
Version: 0.0.103
Summary: Sociable is a platform for making amazing bots
Author-email: Justin Mann <justin.mann@gmail.com>
License: Copyright (c) 2018 The Python Packaging Authority
Project-URL: Homepage, https://sociable.bot
Project-URL: Issues, https://github.com/Effective-Nihilists/sociable_bot/issues
Project-URL: Documentation, https://docs.sociable.bot
Classifier: Programming Language :: Python :: 3
Classifier: Operating System :: OS Independent
Requires-Python: >=3.8
License-File: LICENSE.txt
Requires-Dist: python-socketio
Requires-Dist: websocket-client
Requires-Dist: requests
Dynamic: license-file
